flask_wx_oauth
