Metadata-Version: 1.0
Name: Flask-WX-OAuth
Version: 0.1.3
Summary: Flask Extension for wechat oauth2.0.
Home-page: https://github.com/codeif/Flask-WX-OAuth
Author: codeif
Author-email: me@codeif.com
License: MIT
Platform: UNKNOWN
